bulb/__init__.py
bulb/settings.py
bulb/contrib/__init__.py
bulb/contrib/activity/__init__.py
bulb/contrib/activity/urls.py
bulb/contrib/activity/views.py
bulb/contrib/activity/static/activity/css/background_style/0_activity_general_page.scss
bulb/contrib/activity/static/activity/css/background_style/1_activity_small_page.scss
bulb/contrib/activity/static/activity/css/background_style/2_activity_medium_page.scss
bulb/contrib/activity/static/activity/css/background_style/3_activity_large_page.scss
bulb/contrib/activity/static/activity/css/style/activity_page.scss
bulb/contrib/activity/templates/activity/pages/activity_page.html
bulb/contrib/admin/__init__.py
bulb/contrib/admin/context_processors.py
bulb/contrib/admin/forms.py
bulb/contrib/admin/node_models.py
bulb/contrib/admin/urls.py
bulb/contrib/admin/views.py
bulb/contrib/admin/static/admin/css/background_style/0_admin_home_general_page.scss
bulb/contrib/admin/static/admin/css/background_style/0_base_general_page.scss
bulb/contrib/admin/static/admin/css/background_style/1_admin_home_small_page.scss
bulb/contrib/admin/static/admin/css/background_style/1_base_small_page.scss
bulb/contrib/admin/static/admin/css/background_style/2_admin_home_medium_page.scss
bulb/contrib/admin/static/admin/css/background_style/2_base_medium_page.scss
bulb/contrib/admin/static/admin/css/background_style/3_admin_home_large_page.scss
bulb/contrib/admin/static/admin/css/background_style/3_base_large_page.scss
bulb/contrib/admin/static/admin/css/style/admin_home_page.scss
bulb/contrib/admin/static/admin/css/style/base_page.scss
bulb/contrib/admin/templates/admin/background_pages/base.html
bulb/contrib/admin/templates/admin/background_pages/generic_template.html
bulb/contrib/admin/templates/admin/pages/admin_home.html
bulb/contrib/admin/templates/admin/pages/login.html
bulb/contrib/admin/templatetags/__init__.py
bulb/contrib/admin/templatetags/admin_extras.py
bulb/contrib/auth/__init__.py
bulb/contrib/auth/authentication.py
bulb_core-0.1.22.dist-info/LICENSE
bulb_core-0.1.22.dist-info/METADATA
bulb_core-0.1.22.dist-info/WHEEL
bulb_core-0.1.22.dist-info/top_level.txt
bulb_core-0.1.22.dist-info/RECORD
