Metadata-Version: 2.1
Name: bulb-core
Version: 0.1.22
Summary: Neo4j integration for Django, and much more tools for deployment of consequent websites...
Home-page: https://github.com/LilianCruanes/bulb
Author: Lilian Cruanes
Author-email: cruaneslilian@gmail.com
License: UNKNOWN
Platform: UNKNOWN
Classifier: Intended Audience :: Developers
Classifier: Programming Language :: Python
Classifier: Programming Language :: Python :: 3
Classifier: Programming Language :: Python :: 3 :: Only
Classifier: License :: OSI Approved :: GNU General Public License v3 (GPLv3)
Classifier: Operating System :: OS Independent
Classifier: Framework :: Django
Classifier: Framework :: Django :: 2.2
Classifier: Framework :: Django :: 3.0
Classifier: Natural Language :: English
Classifier: Topic :: Database
Classifier: Topic :: Internet :: File Transfer Protocol (FTP)
Classifier: Topic :: Internet :: WWW/HTTP :: Session
Classifier: Topic :: Internet :: WWW/HTTP :: WSGI
Requires-Dist: Pillow-SIMD
Requires-Dist: bcrypt
Requires-Dist: django-compressor
Requires-Dist: django-libsass
Requires-Dist: lxml
Requires-Dist: neo4j
Requires-Dist: paramiko
Requires-Dist: pysftp
Requires-Dist: requests
Requires-Dist: scour
Provides-Extra: django-libsass
Requires-Dist: django-libsass ; extra == 'django-libsass'
